tdk_cli/__init__.py
tdk_cli/__main__.py
tdk_cli/cli.py
tdk_cli-0.2.1.dist-info/METADATA
tdk_cli-0.2.1.dist-info/WHEEL
tdk_cli-0.2.1.dist-info/entry_points.txt
tdk_cli-0.2.1.dist-info/top_level.txt
tdk_cli-0.2.1.dist-info/RECORD
