Metadata-Version: 2.1
Name: tdk-cli
Version: 0.2.1
Summary: Command-line tool for TDK Dictionary, sozluk.gov.tr with rich output.
Home-page: https://github.com/agmmnn/tdk-cli
Author: agmmnn
License: UNKNOWN
Platform: UNKNOWN
Classifier: Programming Language :: Python :: 3
Classifier: Operating System :: OS Independent
Classifier: Environment :: Console
Classifier: Topic :: Utilities
Requires-Python: >=3.5
Requires-Dist: rich
